ejercicio 3/ejercicio3.v
module ff__D(input wire clock,reset,input wire D,output reg Y);//se crea el flip-flop tipo d para utilizar el circuito
  always @ (posedge clock, posedge reset) begin
    if(reset) begin
      Y <= 1'b0; //un-blocking assignament
    end
    else
      Y <= D;
    end
endmodule

module FSM__Moore(input wire A, clock, reset, output wire Y1, Y2, Y3); //modulo de la maquina de FSM__Moore
                                                                      // que representa el problema 3
    wire S0, S1, S2;

    assign SF0 = ((A & S2 & S1) | (~A & ~S2 & S1) | (~A & S2 & ~S1) | (A & ~S2 & ~S1));
    assign SF1 = ((S1 & ~S0) | (~A & S1 & S2) | (A & ~S2 & S0));
    assign SF2 = ((S2 & S0) | (A & S1 & ~S0) | (~A & ~S1 & ~S0));// ser realizan las conexiones entre nuestros componentes
                                                                // y el estado futuro
    ff__D U1(clock, reset, SF0, S0);// se conecta nuestro circuito y los flip-flops tipo D
    ff__D U2(clock, reset, SF1, S1);
    ff__D U3(clock, reset, SF2, S2);

    assign Y1 = S0;// Se asignan el valor de las variables de salida
    assign Y2 = S1;
    assign Y3 = S2;
endmodule

ejercicio 3/ejercicio3_tb.v
module testbench();

  reg clock,reset;//se inicializan las variables del problema
  reg A;
  wire Y1, Y2, Y3;

  always
    begin
      clock <= 1;
      #1 clock <= ~clock;// se realiza el cambio del reloj
      #1;
  end

 FSM__Moore M1(A, clock, reset, Y1, Y2, Y3);// instanciacion de la maquina de moore

  initial begin
     reset = 1;
     #1 reset = 0; // se realiza el reseteo inicial de la máquina de moore
     $display(" ejercicio 4 - Escala de gray ");
     $display("A | Y1 Y2 Y3");
     $monitor("%b |  %b  %b  %b  ", A, Y3, Y2, Y1);

     A = 1;
    #2 A = 1;
    #2 A = 1;
    #2 A = 1;
    #2 A = 0;
    #2 A = 1;
    #2 A = 1;
    #2 A = 1;
    #2 A = 1;
    #2 A = 1;//se realizan las pruebas necesarias para obtener los valores deseados
    #2 A = 1;
    #2 A = 0;
    #2 A = 0;
    #2 A = 0;
    #2 A = 0;

     #1 $finish;
   end

  initial begin
        $dumpfile("ejercicio3_tb.vcd");// se ejecuta GTKwave
        $dumpvars(0, testbench);
      end

endmodule

ejercicio 3/ejercicio3_tb.vcd
$date
	Sat Sep 05 09:27:35 2020
$end
$version
	Icarus Verilog
$end
$timescale
	1ps
$end
$scope module testbench $end
$var wire 1 ! Y3 $end
$var wire 1 " Y2 $end
$var wire 1 # Y1 $end
$var reg 1 $ A $end
$var reg 1 % clock $end
$var reg 1 & reset $end
$scope module M1 $end
$var wire 1 $ A $end
$var wire 1 ' SF0 $end
$var wire 1 ( SF1 $end
$var wire 1 ) SF2 $end
$var wire 1 # Y1 $end
$var wire 1 " Y2 $end
$var wire 1 ! Y3 $end
$var wire 1 % clock $end
$var wire 1 & reset $end
$var wire 1 * S2 $end
$var wire 1 + S1 $end
$var wire 1 , S0 $end
$scope module U1 $end
$var wire 1 ' D $end
$var wire 1 % clock $end
$var wire 1 & reset $end
$var reg 1 , Y $end
$upscope $end
$scope module U2 $end
$var wire 1 ( D $end
$var wire 1 % clock $end
$var wire 1 & reset $end
$var reg 1 + Y $end
$upscope $end
$scope module U3 $end
$var wire 1 ) D $end
$var wire 1 % clock $end
$var wire 1 & reset $end
$var reg 1 * Y $end
$upscope $end
$upscope $end
$upscope $end
$enddefinitions $end
#0
$dumpvars
0,
0+
0*
x)
0(
x'
1&
1%
x$
0#
0"
0!
$end
#1
0%
0)
1'
1$
0&
#2
1(
1#
1,
1%
#3
0%
#4
0'
1"
1+
1%
#5
0%
#6
1)
1(
0#
0,
1%
#7
0%
#8
1'
1!
1*
1%
#9
0%
0'
0)
0$
#10
1'
0!
0*
1%
#11
0%
0'
1)
1$
#12
1'
1!
1*
1%
#13
0%
#14
0(
1#
1,
1%
#15
0%
#16
0'
0"
0+
1%
#17
0%
#18
0)
0#
0,
1%
#19
0%
#20
1'
0!
0*
1%
#21
0%
#22
1(
1#
1,
1%
#23
0%
0'
0(
0$
#24
1)
0#
0,
1%
#25
0%
#26
1'
1!
1*
1%
#27
0%
#28
1#
1,
1%
